{
  "dogs": [
    {
      "dogName": "Luca",
      "dogBreed": "German Shepherd",
      "id": "1"
    },
    {
      "dogName": "Lola",
      "dogBreed": "Giant Schnauzer",
      "id": "2"
    },
    {
      "id": "e934",
      "dogName": "Byron",
      "dogBreed": "Poodle"
    }
  ],
  "cats": [
    {
      "catName": "Stanley",
      "catBreed": "Tabby",
      "id": "1"
    },
    {
      "catName": "Gunnar",
      "catBreed": "American Shorthair",
      "id": "2"
    }
  ],
  "users": [
    {
      "id": "13ab"
    },
    {
      "id": "4489"
    },
    {
      "id": "76a6"
    },
    {
      "id": "4c49"
    },
    {
      "id": "18b2"
    },
    {
      "id": "3237"
    },
    {
      "id": "6f03"
    },
    {
      "id": "6425"
    },
    {
      "id": "88cb"
    },
    {
      "id": "58d4"
    },
    {
      "id": "d424"
    },
    {
      "id": "400c"
    },
    {
      "id": "b222"
    },
    {
      "id": "6f08"
    },
    {
      "id": "92f8"
    }
  ],
  "robots": [
    {
      "robotName": "C8-09S100K",
      "robotType": "Human Assistant",
      "id": "9000"
    }
  ]
}